README.md
setup.py
abtesting/ABTest.py
abtesting/ZTest.py
abtesting/__init__.py
abtesting.egg-info/PKG-INFO
abtesting.egg-info/SOURCES.txt
abtesting.egg-info/dependency_links.txt
abtesting.egg-info/not-zip-safe
abtesting.egg-info/top_level.txt