Metadata-Version: 1.0
Name: abtesting
Version: 0.1.1
Summary: A simple package for evaluating A/B tests
Home-page: UNKNOWN
Author: Patrick Peltier
Author-email: pa.pe@wtnet.de
License: UNKNOWN
Platform: UNKNOWN
